[["Map",1,2,9,10],"meta::meta",["Map",3,4,5,6,7,8],"astro-version","5.1.8","content-config-digest","08063e5b644833f1","astro-config-digest","{\"root\":{},\"srcDir\":{},\"publicDir\":{},\"outDir\":{},\"cacheDir\":{},\"compressHTML\":true,\"base\":\"/\",\"trailingSlash\":\"ignore\",\"output\":\"static\",\"scopedStyleStrategy\":\"attribute\",\"build\":{\"format\":\"directory\",\"client\":{},\"server\":{},\"assets\":\"_astro\",\"serverEntry\":\"entry.mjs\",\"redirects\":true,\"inlineStylesheets\":\"auto\",\"concurrency\":1},\"server\":{\"open\":false,\"host\":false,\"port\":4321,\"streaming\":true},\"redirects\":{},\"image\":{\"endpoint\":{\"route\":\"/_image\"},\"service\":{\"entrypoint\":\"astro/assets/services/sharp\",\"config\":{}},\"domains\":[],\"remotePatterns\":[]},\"devToolbar\":{\"enabled\":true},\"markdown\":{\"syntaxHighlight\":\"shiki\",\"shikiConfig\":{\"langs\":[],\"langAlias\":{},\"theme\":\"github-dark\",\"themes\":{},\"wrap\":false,\"transformers\":[]},\"remarkPlugins\":[],\"rehypePlugins\":[],\"remarkRehype\":{},\"gfm\":true,\"smartypants\":true},\"security\":{\"checkOrigin\":true},\"env\":{\"schema\":{},\"validateSecrets\":false},\"experimental\":{\"clientPrerender\":false,\"contentIntellisense\":false,\"responsiveImages\":false},\"legacy\":{\"collections\":false}}","episodes",["Map",11,12],"arpa-fvg",{"id":11,"data":13,"filePath":19,"digest":20,"rendered":21},{"title":14,"guest":15,"id":16,"description":17,"url":18},"Quello su ARPA FVG con Sergio Nordio","dr. Sergio Nordio",1,"Nel primo episodio di Oggi fa bora parliamo di meteo e clima con Sergio Nordio, previsore di ARPA FVG. Scopriamo come vengono fatte le previsioni del tempo, quali fenomeni caratterizzano Trieste e dintorni, e come il cambiamento climatico sta influenzando la nostra regione. Bora, temporali improvvisi, estati ed inverni sempre più caldi.","https://anchor.fm/s/1011a8694/podcast/play/99250108/https%3A%2F%2Fd3ctxlq1ktw2nl.cloudfront.net%2Fstaging%2F2025-2-2%2Fc783006e-8b10-98c3-f30d-7d6611e2e0dc.mp3","src/data/episodes/arpa-fvg.md","42201482188ee84a",{"html":22,"metadata":23},"",{"headings":24,"imagePaths":25,"frontmatter":26},[],[],{"id":16,"title":14,"guest":15,"description":17,"url":18}]